bitbuffet/__init__.py
bitbuffet/scraper.py
bitbuffet-1.0.2.dist-info/METADATA
bitbuffet-1.0.2.dist-info/WHEEL
bitbuffet-1.0.2.dist-info/licenses/LICENSE
bitbuffet-1.0.2.dist-info/RECORD
