Metadata-Version: 2.4
Name: bitbuffet
Version: 1.0.2
Summary: Python SDK for the bitbuffet API - BitBuffet
Project-URL: Homepage, https://github.com/ystefanov6/bitbuffet-clients
Project-URL: Repository, https://github.com/ystefanov6/bitbuffet-clients
Project-URL: Documentation, https://github.com/ystefanov6/bitbuffet-clients#readme
Project-URL: Bug Tracker, https://github.com/ystefanov6/bitbuffet-clients/issues
Author-email: Yuliyan Stefanov <ystefanov.dev@gmail.com>
License: MIT
License-File: LICENSE
Keywords: ai,api,client,scraper,structured-data,web-scraping
Classifier: Development Status :: 4 - Beta
Classifier: Intended Audience :: Developers
Classifier: License :: OSI Approved :: MIT License
Classifier: Operating System :: OS Independent
Classifier: Programming Language :: Python :: 3
Classifier: Programming Language :: Python :: 3.8
Classifier: Programming Language :: Python :: 3.9
Classifier: Programming Language :: Python :: 3.10
Classifier: Programming Language :: Python :: 3.11
Classifier: Programming Language :: Python :: 3.12
Classifier: Topic :: Internet :: WWW/HTTP
Classifier: Topic :: Software Development :: Libraries :: Python Modules
Requires-Python: >=3.9
Requires-Dist: build>=1.3.0
Requires-Dist: pydantic>=2.11.7
Requires-Dist: python-dotenv>=1.1.1
Requires-Dist: requests>=2.32.5
Requires-Dist: twine>=6.2.0
